nlptutti/__init__.py
nlptutti/asr_metrics.py
nlptutti-0.0.0.10.dist-info/LICENSE
nlptutti-0.0.0.10.dist-info/METADATA
nlptutti-0.0.0.10.dist-info/WHEEL
nlptutti-0.0.0.10.dist-info/top_level.txt
nlptutti-0.0.0.10.dist-info/RECORD
