Metadata-Version: 2.1
Name: nlptutti
Version: 0.0.0.10
Summary: Korean STT (Speech-to-Text) error rate calculation package
Author-email: hyeonsangjeon <wungnut0310@gmail.com>
License: MIT
Project-URL: Homepage, https://github.com/hyeonsangjeon/computing-Korean-STT-error-rates
Project-URL: Repository, https://github.com/hyeonsangjeon/computing-Korean-STT-error-rates
Project-URL: Documentation, https://github.com/hyeonsangjeon/computing-Korean-STT-error-rates#readme
Project-URL: Bug Tracker, https://github.com/hyeonsangjeon/computing-Korean-STT-error-rates/issues
Keywords: STT,ASR,Korean,NLP,CER,WER,speech recognition
Classifier: Development Status :: 4 - Beta
Classifier: Intended Audience :: Developers
Classifier: Topic :: Scientific/Engineering :: Artificial Intelligence
Classifier: Topic :: Text Processing :: Linguistic
Classifier: License :: OSI Approved :: MIT License
Classifier: Programming Language :: Python :: 3
Classifier: Programming Language :: Python :: 3.7
Classifier: Programming Language :: Python :: 3.8
Classifier: Programming Language :: Python :: 3.9
Classifier: Programming Language :: Python :: 3.10
Classifier: Programming Language :: Python :: 3.11
Requires-Python: >=3.7
License-File: LICENSE
Requires-Dist: jiwer
Requires-Dist: pandas
